zaguan/__init__.py
zaguan/actions.py
zaguan/container.py
zaguan/controller.py
zaguan/engines.py
zaguan/functions.py
zaguan-3.2.2.dist-info/licenses/LICENSE.txt
zaguan-3.2.2.dist-info/METADATA
zaguan-3.2.2.dist-info/WHEEL
zaguan-3.2.2.dist-info/top_level.txt
zaguan-3.2.2.dist-info/RECORD
