Metadata-Version: 2.4
Name: zaguan
Version: 3.2.2
Summary: Front end framework to develop apps with webkit an pygtk
Home-page: http://pypi.python.org/pypi/zaguan/
Author: Luis Andres Giordano
Author-email: agiordano@msa.com.ar
License: LICENSE.txt
License-File: LICENSE.txt
Dynamic: author
Dynamic: author-email
Dynamic: home-page
Dynamic: license
Dynamic: license-file
Dynamic: summary
